LICENSE
README.md
setup.cfg
setup.py
tsshapelet/__init__.py
tsshapelet/barycenters.py
tsshapelet/comparator.py
tsshapelet/features.py
tsshapelet/metrics.py
tsshapelet/shapelet.py
tsshapelet/utils.py
tsshapelet.egg-info/PKG-INFO
tsshapelet.egg-info/SOURCES.txt
tsshapelet.egg-info/dependency_links.txt
tsshapelet.egg-info/requires.txt
tsshapelet.egg-info/top_level.txt