Metadata-Version: 2.1
Name: tsshapelet
Version: 2.2.1
Summary: A timeseries shapelet extraction tool for python.
Home-page: https://github.com/gellison321/tsshapelet
Download-URL: https://github.com/gellison321/tsshapelet/archive/refs/tags/2.2.1.tar.gz
Author: Grant Ellison
Author-email: gellison321@gmail.com
Keywords: timeseries,barycenter,data science,data analysis
Classifier: Development Status :: 4 - Beta
Classifier: Intended Audience :: Developers
Classifier: Intended Audience :: Science/Research
Classifier: Topic :: Software Development :: Build Tools
Classifier: Operating System :: OS Independent
Classifier: License :: OSI Approved :: MIT License
Classifier: Programming Language :: Python
License-File: LICENSE
